{
  "api/Global.HitInfoManager.html": {
    "href": "api/Global.HitInfoManager.html",
    "title": "Class HitInfoManager | JMR Samples",
    "keywords": "Class HitInfoManager Inheritance Object HitInfoManager Namespace : Global Assembly : cs.temp.dll.dll Syntax public class HitInfoManager : MonoBehaviour Methods CursorInfo() Get JMRPointerObject and update it on UI. Declaration public void CursorInfo()"
  },
  "api/Global.html": {
    "href": "api/Global.html",
    "title": "Namespace Global | JMR Samples",
    "keywords": "Namespace Global Classes HitInfoManager"
  },
  "index.html": {
    "href": "index.html",
    "title": "ExampleSnippets-RaycastInfo | JMR Samples",
    "keywords": "ExampleSnippets-RaycastInfo Get Information about the raycast"
  },
  "manual/JMRSamples.html": {
    "href": "manual/JMRSamples.html",
    "title": "Sample | JMR Samples",
    "keywords": "Sample"
  }
}